{
  "Version": "1.0.0.0",
  "LastState": 11,
  "Modules": [
    {
      "ModuleName": "Front Left",
      "ModuleId": 0,
      "Encoder": {
        "Id": 3,
        "Name": "Front_Left",
        "Model": "CANCoder",
        "CANbus": "45D3FE4C463847532020204B151D0DFF",
        "CANbusFriendly": "drive train",
        "SelectedMotorType": null
      },
      "SteerMotor": {
        "Id": 10,
        "Name": "FrontLeft_Steer",
        "Model": "Talon FX vers. F",
        "CANbus": "45D3FE4C463847532020204B151D0DFF",
        "CANbusFriendly": "drive train",
        "SelectedMotorType": {
          "Name": "WCP Kraken x44",
          "FreeSpeedRps": 125.5,
          "SlipCurrentLimit": 120,
          "StatorCurrentLimit": 60
        }
      },
      "DriveMotor": {
        "Id": 9,
        "Name": "FrontLeft_Drive",
        "Model": "Talon FX vers. C",
        "CANbus": "45D3FE4C463847532020204B151D0DFF",
        "CANbusFriendly": "drive train",
        "SelectedMotorType": {
          "Name": "WCP Kraken x60",
          "FreeSpeedRps": 96.7,
          "SlipCurrentLimit": 120,
          "StatorCurrentLimit": 60
        }
      },
      "IsEncoderInverted": false,
      "IsSteerInverted": false,
      "SelectedEncoderType": "CANcoder",
      "EncoderOffset": -0.239501953125,
      "DriveMotorSelectionState": 1,
      "SteerMotorSelectionState": 1,
      "SteerEncoderSelectionState": 1,
      "IsModuleValidationComplete": true,
      "ValidatedSteerId": 10,
      "ValidatedDriveId": 9,
      "ValidatedEncoderId": 3
    },
    {
      "ModuleName": "Front Right",
      "ModuleId": 1,
      "Encoder": {
        "Id": 4,
        "Name": "Front_Right",
        "Model": "CANCoder",
        "CANbus": "45D3FE4C463847532020204B151D0DFF",
        "CANbusFriendly": "drive train",
        "SelectedMotorType": null
      },
      "SteerMotor": {
        "Id": 16,
        "Name": "FrontRight_Steer",
        "Model": "Talon FX vers. F",
        "CANbus": "45D3FE4C463847532020204B151D0DFF",
        "CANbusFriendly": "drive train",
        "SelectedMotorType": {
          "Name": "WCP Kraken x44",
          "FreeSpeedRps": 125.5,
          "SlipCurrentLimit": 120,
          "StatorCurrentLimit": 60
        }
      },
      "DriveMotor": {
        "Id": 6,
        "Name": "FrontRight_Drive",
        "Model": "Talon FX vers. C",
        "CANbus": "45D3FE4C463847532020204B151D0DFF",
        "CANbusFriendly": "drive train",
        "SelectedMotorType": {
          "Name": "WCP Kraken x60",
          "FreeSpeedRps": 96.7,
          "SlipCurrentLimit": 120,
          "StatorCurrentLimit": 60
        }
      },
      "IsEncoderInverted": false,
      "IsSteerInverted": false,
      "SelectedEncoderType": "CANcoder",
      "EncoderOffset": -0.0234375,
      "DriveMotorSelectionState": 1,
      "SteerMotorSelectionState": 1,
      "SteerEncoderSelectionState": 1,
      "IsModuleValidationComplete": true,
      "ValidatedSteerId": 16,
      "ValidatedDriveId": 6,
      "ValidatedEncoderId": 4
    },
    {
      "ModuleName": "Back Left",
      "ModuleId": 2,
      "Encoder": {
        "Id": 2,
        "Name": "Back_Left",
        "Model": "CANCoder",
        "CANbus": "45D3FE4C463847532020204B151D0DFF",
        "CANbusFriendly": "drive train",
        "SelectedMotorType": null
      },
      "SteerMotor": {
        "Id": 7,
        "Name": "BackLeft_Steer",
        "Model": "Talon FX vers. F",
        "CANbus": "45D3FE4C463847532020204B151D0DFF",
        "CANbusFriendly": "drive train",
        "SelectedMotorType": {
          "Name": "WCP Kraken x44",
          "FreeSpeedRps": 125.5,
          "SlipCurrentLimit": 120,
          "StatorCurrentLimit": 60
        }
      },
      "DriveMotor": {
        "Id": 5,
        "Name": "BackLeft_Drive",
        "Model": "Talon FX vers. C",
        "CANbus": "45D3FE4C463847532020204B151D0DFF",
        "CANbusFriendly": "drive train",
        "SelectedMotorType": {
          "Name": "WCP Kraken x60",
          "FreeSpeedRps": 96.7,
          "SlipCurrentLimit": 120,
          "StatorCurrentLimit": 60
        }
      },
      "IsEncoderInverted": false,
      "IsSteerInverted": false,
      "SelectedEncoderType": "CANcoder",
      "EncoderOffset": 0.257080078125,
      "DriveMotorSelectionState": 1,
      "SteerMotorSelectionState": 1,
      "SteerEncoderSelectionState": 1,
      "IsModuleValidationComplete": true,
      "ValidatedSteerId": 7,
      "ValidatedDriveId": 5,
      "ValidatedEncoderId": 2
    },
    {
      "ModuleName": "Back Right",
      "ModuleId": 3,
      "Encoder": {
        "Id": 1,
        "Name": "Back_Right",
        "Model": "CANCoder",
        "CANbus": "45D3FE4C463847532020204B151D0DFF",
        "CANbusFriendly": "drive train",
        "SelectedMotorType": null
      },
      "SteerMotor": {
        "Id": 12,
        "Name": "BackRight_Steer",
        "Model": "Talon FX vers. F",
        "CANbus": "45D3FE4C463847532020204B151D0DFF",
        "CANbusFriendly": "drive train",
        "SelectedMotorType": {
          "Name": "WCP Kraken x44",
          "FreeSpeedRps": 125.5,
          "SlipCurrentLimit": 120,
          "StatorCurrentLimit": 60
        }
      },
      "DriveMotor": {
        "Id": 11,
        "Name": "BackRight_Drive",
        "Model": "Talon FX vers. C",
        "CANbus": "45D3FE4C463847532020204B151D0DFF",
        "CANbusFriendly": "drive train",
        "SelectedMotorType": {
          "Name": "WCP Kraken x60",
          "FreeSpeedRps": 96.7,
          "SlipCurrentLimit": 120,
          "StatorCurrentLimit": 60
        }
      },
      "IsEncoderInverted": false,
      "IsSteerInverted": false,
      "SelectedEncoderType": "CANcoder",
      "EncoderOffset": -0.42529296875,
      "DriveMotorSelectionState": 1,
      "SteerMotorSelectionState": 1,
      "SteerEncoderSelectionState": 1,
      "IsModuleValidationComplete": true,
      "ValidatedSteerId": 12,
      "ValidatedDriveId": 11,
      "ValidatedEncoderId": 1
    }
  ],
  "SwerveOptions": {
    "Gyro": {
      "Id": 0,
      "Name": "Pigeon 2 vers. S (Device ID 0)",
      "Model": "Pigeon 2 vers. S",
      "CANbus": "45D3FE4C463847532020204B151D0DFF",
      "CANbusFriendly": "drive train",
      "SelectedMotorType": null
    },
    "IsValidGyroCANbus": true,
    "VerticalTrackSizeInches": 21.0,
    "HorizontalTrackSizeInches": 21.0,
    "WheelRadiusInches": 2.0,
    "IsLeftSideInverted": false,
    "IsRightSideInverted": true,
    "SwerveModuleType": 7,
    "SwerveModuleConfiguration": {
      "ModuleBrand": 7,
      "DriveRatio": 6.026785714285714,
      "SteerRatio": 26.09090909090909,
      "CouplingRatio": 3.857142857142857,
      "CustomName": "R2"
    },
    "HasVerifiedSteer": true,
    "SelectedModuleManufacturer": "Swerve Drive Specialties (SDS)",
    "HasVerifiedDrive": true,
    "IsValidConfiguration": true
  },
  "TeamNumber": 6242,
  "schema_version": "1"
}